wltr_vin/__init__.py
wltr_vin/brands.py
wltr_vin/cli.py
wltr_vin/common.py
wltr_vin/exceptions.py
wltr_vin/toolbox.py
wltr_vin/utils.py
wltr_vin/details/__init__.py
wltr_vin/details/_base.py
wltr_vin/details/avtovaz.py
wltr_vin/details/nissan.py
wltr_vin/details/opel.py
wltr_vin/details/renault.py
wltr_vin/dicts/__init__.py
wltr_vin/dicts/bodies.py
wltr_vin/dicts/countries.py
wltr_vin/dicts/regions.py
wltr_vin/dicts/wmi.py
wltr_vin-1.1.0.dist-info/AUTHORS
wltr_vin-1.1.0.dist-info/LICENSE
wltr_vin-1.1.0.dist-info/METADATA
wltr_vin-1.1.0.dist-info/WHEEL
wltr_vin-1.1.0.dist-info/entry_points.txt
wltr_vin-1.1.0.dist-info/top_level.txt
wltr_vin-1.1.0.dist-info/RECORD
