Metadata-Version: 2.1
Name: wltr-vin
Version: 1.1.0
Summary: Extracts useful information from Vehicle Identification Number (VIN)
Home-page: https://github.com/walteravelino/wltr-vin
Author: Walter José Avelino da Silva
Author-email: walter.avelin@gmail.com
License: UNKNOWN
Platform: UNKNOWN
Classifier: Programming Language :: Python :: 3
Classifier: License :: OSI Approved :: MIT License
Classifier: Operating System :: OS Independent
License-File: LICENSE
License-File: AUTHORS
Provides-Extra: cli
Requires-Dist: click ; extra == 'cli'
